cmlibs/__init__.py
cmlibs/utils/__init__.py
cmlibs/utils/image.py
cmlibs/utils/geometry/__init__.py
cmlibs/utils/geometry/plane.py
cmlibs/utils/zinc/__init__.py
cmlibs/utils/zinc/field.py
cmlibs/utils/zinc/finiteelement.py
cmlibs/utils/zinc/general.py
cmlibs/utils/zinc/group.py
cmlibs/utils/zinc/material.py
cmlibs/utils/zinc/mesh.py
cmlibs/utils/zinc/meshrefinement.py
cmlibs/utils/zinc/node.py
cmlibs/utils/zinc/region.py
cmlibs/utils/zinc/scene.py
cmlibs_utils-0.13.0.dist-info/licenses/LICENSE
cmlibs_utils-0.13.0.dist-info/METADATA
cmlibs_utils-0.13.0.dist-info/WHEEL
cmlibs_utils-0.13.0.dist-info/top_level.txt
cmlibs_utils-0.13.0.dist-info/RECORD
