Metadata-Version: 2.4
Name: cmlibs.utils
Version: 0.13.0
Summary: Utilities for the CMLibs Zinc library.
Author-email: Hugh Sorby <h.sorby@auckland.ac.nz>
License-Expression: Apache-2.0
Project-URL: Homepage, https://cmlibs.org
Project-URL: Repository, https://github.com/CMLibs-Python/cmlibs.utils
Keywords: Utilities,CMLibs,Zinc
Classifier: Programming Language :: Python :: 3
Classifier: Operating System :: OS Independent
Classifier: Topic :: Scientific/Engineering :: Medical Science Apps.
Requires-Python: >=3.8
License-File: LICENSE
Requires-Dist: cmlibs.maths>=0.5
Requires-Dist: cmlibs.zinc>=4.1.3
Dynamic: license-file
